{
  "moduleName": "园区碳排放估算模块",
  "method": "园区估算 CO2 = 苏州市 CO2 × 园区经济活动占比",
  "assumptions": [
    "第一版未接入园区企业用电、天然气、热力和过程排放数据。",
    "园区经济活动占比采用 14.8%（演示情景假设，可替换为园区 GDP 或工业增加值真实占比）。",
    "估算结果用于趋势展示和方案答辩，不替代企业碳核算或政府正式清单。"
  ],
  "preferredFutureMethod": "能源消费法：电力消费×电网排放因子 + 天然气消费×排放因子 + 热力消费×排放因子。",
  "records": [
    {
      "year": 2000,
      "city_co2_emission": 40.38,
      "park_estimated_co2": 5.98,
      "park_estimated_10k_tons": 597.6,
      "unit": "百万吨 CO2",
      "method": "经济活动分摊法",
      "activity_share": 0.148,
      "activity_share_label": "14.8%（演示情景假设，可替换为园区 GDP 或工业增加值真实占比）",
      "source": "中国290个城市碳排放清单",
      "confidence": "情景估算"
    },
    {
      "year": 2001,
      "city_co2_emission": 46.21,
      "park_estimated_co2": 6.84,
      "park_estimated_10k_tons": 683.9,
      "unit": "百万吨 CO2",
      "method": "经济活动分摊法",
      "activity_share": 0.148,
      "activity_share_label": "14.8%（演示情景假设，可替换为园区 GDP 或工业增加值真实占比）",
      "source": "中国290个城市碳排放清单",
      "confidence": "情景估算"
    },
    {
      "year": 2002,
      "city_co2_emission": 39.94,
      "park_estimated_co2": 5.91,
      "park_estimated_10k_tons": 591.1,
      "unit": "百万吨 CO2",
      "method": "经济活动分摊法",
      "activity_share": 0.148,
      "activity_share_label": "14.8%（演示情景假设，可替换为园区 GDP 或工业增加值真实占比）",
      "source": "中国290个城市碳排放清单",
      "confidence": "情景估算"
    },
    {
      "year": 2003,
      "city_co2_emission": 58.14,
      "park_estimated_co2": 8.6,
      "park_estimated_10k_tons": 860.5,
      "unit": "百万吨 CO2",
      "method": "经济活动分摊法",
      "activity_share": 0.148,
      "activity_share_label": "14.8%（演示情景假设，可替换为园区 GDP 或工业增加值真实占比）",
      "source": "中国290个城市碳排放清单",
      "confidence": "情景估算"
    },
    {
      "year": 2004,
      "city_co2_emission": 73.23,
      "park_estimated_co2": 10.84,
      "park_estimated_10k_tons": 1083.8,
      "unit": "百万吨 CO2",
      "method": "经济活动分摊法",
      "activity_share": 0.148,
      "activity_share_label": "14.8%（演示情景假设，可替换为园区 GDP 或工业增加值真实占比）",
      "source": "中国290个城市碳排放清单",
      "confidence": "情景估算"
    },
    {
      "year": 2005,
      "city_co2_emission": 103.4,
      "park_estimated_co2": 15.3,
      "park_estimated_10k_tons": 1530.3,
      "unit": "百万吨 CO2",
      "method": "经济活动分摊法",
      "activity_share": 0.148,
      "activity_share_label": "14.8%（演示情景假设，可替换为园区 GDP 或工业增加值真实占比）",
      "source": "中国290个城市碳排放清单",
      "confidence": "情景估算"
    },
    {
      "year": 2006,
      "city_co2_emission": 127.55,
      "park_estimated_co2": 18.88,
      "park_estimated_10k_tons": 1887.7,
      "unit": "百万吨 CO2",
      "method": "经济活动分摊法",
      "activity_share": 0.148,
      "activity_share_label": "14.8%（演示情景假设，可替换为园区 GDP 或工业增加值真实占比）",
      "source": "中国290个城市碳排放清单",
      "confidence": "情景估算"
    },
    {
      "year": 2007,
      "city_co2_emission": 147.7,
      "park_estimated_co2": 21.86,
      "park_estimated_10k_tons": 2186.0,
      "unit": "百万吨 CO2",
      "method": "经济活动分摊法",
      "activity_share": 0.148,
      "activity_share_label": "14.8%（演示情景假设，可替换为园区 GDP 或工业增加值真实占比）",
      "source": "中国290个城市碳排放清单",
      "confidence": "情景估算"
    },
    {
      "year": 2008,
      "city_co2_emission": 150.06,
      "park_estimated_co2": 22.21,
      "park_estimated_10k_tons": 2220.9,
      "unit": "百万吨 CO2",
      "method": "经济活动分摊法",
      "activity_share": 0.148,
      "activity_share_label": "14.8%（演示情景假设，可替换为园区 GDP 或工业增加值真实占比）",
      "source": "中国290个城市碳排放清单",
      "confidence": "情景估算"
    },
    {
      "year": 2009,
      "city_co2_emission": 167.4,
      "park_estimated_co2": 24.78,
      "park_estimated_10k_tons": 2477.5,
      "unit": "百万吨 CO2",
      "method": "经济活动分摊法",
      "activity_share": 0.148,
      "activity_share_label": "14.8%（演示情景假设，可替换为园区 GDP 或工业增加值真实占比）",
      "source": "中国290个城市碳排放清单",
      "confidence": "情景估算"
    },
    {
      "year": 2010,
      "city_co2_emission": 184.61,
      "park_estimated_co2": 27.32,
      "park_estimated_10k_tons": 2732.2,
      "unit": "百万吨 CO2",
      "method": "经济活动分摊法",
      "activity_share": 0.148,
      "activity_share_label": "14.8%（演示情景假设，可替换为园区 GDP 或工业增加值真实占比）",
      "source": "中国290个城市碳排放清单",
      "confidence": "情景估算"
    },
    {
      "year": 2011,
      "city_co2_emission": 202.11,
      "park_estimated_co2": 29.91,
      "park_estimated_10k_tons": 2991.2,
      "unit": "百万吨 CO2",
      "method": "经济活动分摊法",
      "activity_share": 0.148,
      "activity_share_label": "14.8%（演示情景假设，可替换为园区 GDP 或工业增加值真实占比）",
      "source": "中国290个城市碳排放清单",
      "confidence": "情景估算"
    },
    {
      "year": 2012,
      "city_co2_emission": 207.79,
      "park_estimated_co2": 30.75,
      "park_estimated_10k_tons": 3075.3,
      "unit": "百万吨 CO2",
      "method": "经济活动分摊法",
      "activity_share": 0.148,
      "activity_share_label": "14.8%（演示情景假设，可替换为园区 GDP 或工业增加值真实占比）",
      "source": "中国290个城市碳排放清单",
      "confidence": "情景估算"
    },
    {
      "year": 2013,
      "city_co2_emission": 218.38,
      "park_estimated_co2": 32.32,
      "park_estimated_10k_tons": 3232.0,
      "unit": "百万吨 CO2",
      "method": "经济活动分摊法",
      "activity_share": 0.148,
      "activity_share_label": "14.8%（演示情景假设，可替换为园区 GDP 或工业增加值真实占比）",
      "source": "中国290个城市碳排放清单",
      "confidence": "情景估算"
    },
    {
      "year": 2014,
      "city_co2_emission": 221.49,
      "park_estimated_co2": 32.78,
      "park_estimated_10k_tons": 3278.1,
      "unit": "百万吨 CO2",
      "method": "经济活动分摊法",
      "activity_share": 0.148,
      "activity_share_label": "14.8%（演示情景假设，可替换为园区 GDP 或工业增加值真实占比）",
      "source": "中国290个城市碳排放清单",
      "confidence": "情景估算"
    },
    {
      "year": 2015,
      "city_co2_emission": 236.49,
      "park_estimated_co2": 35.0,
      "park_estimated_10k_tons": 3500.1,
      "unit": "百万吨 CO2",
      "method": "经济活动分摊法",
      "activity_share": 0.148,
      "activity_share_label": "14.8%（演示情景假设，可替换为园区 GDP 或工业增加值真实占比）",
      "source": "中国290个城市碳排放清单",
      "confidence": "情景估算"
    },
    {
      "year": 2016,
      "city_co2_emission": 211.96,
      "park_estimated_co2": 31.37,
      "park_estimated_10k_tons": 3137.0,
      "unit": "百万吨 CO2",
      "method": "经济活动分摊法",
      "activity_share": 0.148,
      "activity_share_label": "14.8%（演示情景假设，可替换为园区 GDP 或工业增加值真实占比）",
      "source": "中国290个城市碳排放清单",
      "confidence": "情景估算"
    },
    {
      "year": 2017,
      "city_co2_emission": 206.9,
      "park_estimated_co2": 30.62,
      "park_estimated_10k_tons": 3062.1,
      "unit": "百万吨 CO2",
      "method": "经济活动分摊法",
      "activity_share": 0.148,
      "activity_share_label": "14.8%（演示情景假设，可替换为园区 GDP 或工业增加值真实占比）",
      "source": "中国290个城市碳排放清单",
      "confidence": "情景估算"
    },
    {
      "year": 2018,
      "city_co2_emission": 213.41,
      "park_estimated_co2": 31.58,
      "park_estimated_10k_tons": 3158.5,
      "unit": "百万吨 CO2",
      "method": "经济活动分摊法",
      "activity_share": 0.148,
      "activity_share_label": "14.8%（演示情景假设，可替换为园区 GDP 或工业增加值真实占比）",
      "source": "中国290个城市碳排放清单",
      "confidence": "情景估算"
    },
    {
      "year": 2019,
      "city_co2_emission": 231.19,
      "park_estimated_co2": 34.22,
      "park_estimated_10k_tons": 3421.6,
      "unit": "百万吨 CO2",
      "method": "经济活动分摊法",
      "activity_share": 0.148,
      "activity_share_label": "14.8%（演示情景假设，可替换为园区 GDP 或工业增加值真实占比）",
      "source": "中国290个城市碳排放清单",
      "confidence": "情景估算"
    }
  ],
  "latest": {
    "year": 2019,
    "city_co2_emission": 231.19,
    "park_estimated_co2": 34.22,
    "park_estimated_10k_tons": 3421.6,
    "unit": "百万吨 CO2",
    "method": "经济活动分摊法",
    "activity_share": 0.148,
    "activity_share_label": "14.8%（演示情景假设，可替换为园区 GDP 或工业增加值真实占比）",
    "source": "中国290个城市碳排放清单",
    "confidence": "情景估算"
  }
}